mapcode.cpython-37m-darwin.so
mapcode-2.5.5.0.dist-info/LICENSE
mapcode-2.5.5.0.dist-info/METADATA
mapcode-2.5.5.0.dist-info/WHEEL
mapcode-2.5.5.0.dist-info/top_level.txt
mapcode-2.5.5.0.dist-info/RECORD
