Metadata-Version: 2.1
Name: mapcode
Version: 2.5.5.0
Summary: A Python module to do mapcode encoding and decoding. See http://www.mapcode.com for more information.
Home-page: https://github.com/mapcode-foundation/mapcode-python
Author: Erik Bos
Author-email: erik@xs4all.nl
License: Apache License 2.0
Download-URL: https://github.com/mapcode-foundation/mapcode-python/tarball/v2.5.5.0
Platform: UNKNOWN
Classifier: Development Status :: 5 - Production/Stable
Classifier: Topic :: Scientific/Engineering :: GIS
Classifier: License :: OSI Approved :: Apache Software License
Classifier: Programming Language :: Python :: 2.6
Classifier: Programming Language :: Python :: 2.7
Classifier: Programming Language :: Python :: 3
